crawler_to_md/__init__.py
crawler_to_md/cli.py
crawler_to_md/database_manager.py
crawler_to_md/export_manager.py
crawler_to_md/log_setup.py
crawler_to_md/scraper.py
crawler_to_md/utils.py
crawler_to_md-0.5.0.dist-info/METADATA
crawler_to_md-0.5.0.dist-info/WHEEL
crawler_to_md-0.5.0.dist-info/entry_points.txt
crawler_to_md-0.5.0.dist-info/top_level.txt
crawler_to_md-0.5.0.dist-info/RECORD
