Metadata-Version: 2.4
Name: crawler-to-md
Version: 0.5.0
Summary: Convert web content to Markdown & JSON files to fuel your GPTs and agent AI!
Author-email: "Grégoire Compagnon (obeone)" <obeone@obeone.org>
License-Expression: MIT
Project-URL: Homepage, https://github.com/obeone/crawler-to-md
Project-URL: Bug_Tracker, https://github.com/obeone/crawler-to-md/issues
Classifier: Development Status :: 3 - Alpha
Classifier: Intended Audience :: Developers
Classifier: Topic :: Software Development :: Build Tools
Classifier: Programming Language :: Python :: 3
Classifier: Programming Language :: Python :: 3.10
Classifier: Programming Language :: Python :: 3.11
Classifier: Programming Language :: Python :: 3.12
Requires-Python: >=3.10
Requires-Dist: mdformat==0.7.22
Requires-Dist: mdformat-gfm==0.4.1
Requires-Dist: mdformat_footnote==0.1.1
Requires-Dist: mdformat_frontmatter==2.0.8
Requires-Dist: mdformat_tables==1.0.0
Requires-Dist: requests[socks]==2.32.4
Requires-Dist: tqdm==4.67.1
Requires-Dist: markitdown==0.1.2
Requires-Dist: coloredlogs==15.0.1
Requires-Dist: beautifulsoup4==4.13.4
Requires-Dist: argcomplete==3.6.2
